calisim/__init__.py
calisim/abc/__init__.py
calisim/abc/implementation.py
calisim/abc/pyabc_wrapper.py
calisim/abc/pymc_wrapper.py
calisim/active_learning/__init__.py
calisim/active_learning/implementation.py
calisim/active_learning/skactiveml_wrapper.py
calisim/base/__init__.py
calisim/base/calibration_base.py
calisim/base/emukit_base.py
calisim/base/example_model_base.py
calisim/base/history_matching_base.py
calisim/base/openturns_base.py
calisim/base/sbi_base.py
calisim/base/surrogate_base.py
calisim/bayesian/__init__.py
calisim/bayesian/emcee_wrapper.py
calisim/bayesian/implementation.py
calisim/bayesian/openturns_wrapper.py
calisim/data_model/__init__.py
calisim/data_model/simulation_data_models.py
calisim/estimators/__init__.py
calisim/estimators/emukit_estimator.py
calisim/estimators/gpytorch_estimator.py
calisim/estimators/openturns_estimator.py
calisim/evolutionary/__init__.py
calisim/evolutionary/evotorch_wrapper.py
calisim/evolutionary/implementation.py
calisim/evolutionary/spotpy_wrapper.py
calisim/example_models/__init__.py
calisim/example_models/anharmonic_oscillator.py
calisim/example_models/lorenz_95.py
calisim/example_models/lotka_volterra.py
calisim/example_models/sir_ode.py
calisim/experimental/__init__.py
calisim/experimental/abc/__init__.py
calisim/experimental/abc/elfi_wrapper.py
calisim/experimental/base/__init__.py
calisim/experimental/base/elfi_base.py
calisim/experimental/likelihood_free/__init__.py
calisim/experimental/likelihood_free/elfi_wrapper.py
calisim/experimental/state_estimation/__init__.py
calisim/experimental/state_estimation/ensemble_kalman_filter.py
calisim/experimental/state_estimation/implementation.py
calisim/experimental_design/__init__.py
calisim/experimental_design/emukit_wrapper.py
calisim/experimental_design/implementation.py
calisim/history_matching/__init__.py
calisim/history_matching/ies_wrapper.py
calisim/history_matching/implementation.py
calisim/history_matching/pyesmda_wrapper.py
calisim-0.6.2.dist-info/LICENSE
calisim-0.6.2.dist-info/METADATA
calisim-0.6.2.dist-info/WHEEL
calisim-0.6.2.dist-info/RECORD
